csi_preprocess/ActivitySegmentation.py
csi_preprocess/AntenaSelection.py
csi_preprocess/ConjMulti.py
csi_preprocess/DWT.py
csi_preprocess/EMD.py
csi_preprocess/EPIAR.py
csi_preprocess/Filter.py
csi_preprocess/LDA.py
csi_preprocess/LineaTtransform.py
csi_preprocess/LinearFitting.py
csi_preprocess/PCA.py
csi_preprocess/PhaseRatio.py
csi_preprocess/SlideWindow.py
csi_preprocess/SubEnv.py
csi_preprocess/WMA.py
csi_preprocess/__init__.py
csi_preprocess-0.0.3.dist-info/LICENSE
csi_preprocess-0.0.3.dist-info/METADATA
csi_preprocess-0.0.3.dist-info/WHEEL
csi_preprocess-0.0.3.dist-info/top_level.txt
csi_preprocess-0.0.3.dist-info/RECORD
