Metadata-Version: 2.1
Name: csi-preprocess
Version: 0.0.3
Summary: A collection of public preprocess method for CSI data.
Home-page: https://github.com/ykoneee
Author: Kang Yin
Author-email: yinkanggm@gmail.com
License: UNKNOWN
Platform: UNKNOWN
Classifier: Programming Language :: Python :: 3
Classifier: License :: OSI Approved :: MIT License
Classifier: Operating System :: OS Independent
Classifier: Topic :: Scientific/Engineering
Requires-Python: >=3.6
License-File: LICENSE
Requires-Dist: numpy
Requires-Dist: numba
Requires-Dist: scikit-learn
Requires-Dist: EMD-signal
Requires-Dist: PyWavelets
